openreason/__init__.py
openreason/main.py
openreason-0.0.1a2.dist-info/METADATA
openreason-0.0.1a2.dist-info/WHEEL
openreason-0.0.1a2.dist-info/top_level.txt
openreason-0.0.1a2.dist-info/RECORD
