Metadata-Version: 2.2
Name: openreason
Version: 0.0.1a2
Summary: OpenReason is a Python framework to build reasoning agents with O1/O3 and R1.
Author: Genmo
Author-email: Genmo <hi@genmo.ai>
Project-URL: Homepage, https://openreason.ai
Classifier: Development Status :: 2 - Pre-Alpha
Classifier: Programming Language :: Python :: 3
Classifier: License :: OSI Approved :: MIT License
Classifier: Operating System :: OS Independent
Requires-Python: >=3.6
